organizer/__init__.py
organizer/actions.py
organizer_girvel-1.0.0.dist-info/METADATA
organizer_girvel-1.0.0.dist-info/WHEEL
organizer_girvel-1.0.0.dist-info/top_level.txt
organizer_girvel-1.0.0.dist-info/RECORD
