Metadata-Version: 2.1
Name: organizer-girvel
Version: 1.0.0
Summary: This is very simple logging application for tracking your daily activities
Home-page: https://github.com/girvel/organizer
Author: girvel
Author-email: widauka@yandex.ru
License: UNKNOWN
Platform: UNKNOWN
Classifier: Programming Language :: Python :: 3
Classifier: License :: OSI Approved :: MIT License
Classifier: Operating System :: OS Independent
Requires-Python: >=3.6
Requires-Dist: termcolor
Requires-Dist: text-actions-girvel
